aptai/__init__.py
aptai-1.2.2.dist-info/METADATA
aptai-1.2.2.dist-info/WHEEL
aptai-1.2.2.dist-info/top_level.txt
aptai-1.2.2.dist-info/RECORD
