Metadata-Version: 2.2
Name: aptai
Version: 1.2.2
Summary: Advanced AI-powered SDK for DeFi & NFT analytics on Aptos
Author: Teck
Project-URL: Homepage, https://github.com/Teck/aptai
Project-URL: X, https://x.com/Teckdegen
Project-URL: Telegram, https://t.me/Teck_degen
Classifier: Programming Language :: Python :: 3
Classifier: License :: OSI Approved :: MIT License
Classifier: Operating System :: OS Independent
Requires-Python: >=3.11
Requires-Dist: requests
Requires-Dist: groq
Requires-Dist: setuptools>=76.0.0
